Workbook

Sheet Raw_Data
A1: Order ID | B1: Order Date | C1: Region | D1: Category | E1: Product | F1: Quantity | G1: Unit Price | H1: Discount
A2: ORD001 | B2: 45662 | C2: North | D2: Electronics | E2: Wireless Headphones | F2: 3 | G2: 1499 | H2: 0.05
A3: ORD002 | B3: 45665 | C3: South | D3: Furniture | E3: Office Chair | F3: 2 | G3: 4999 | H3: 0.1
A4: ORD003 | B4: 45669 | C4: East | D4: Office Supplies | E4: Notebook | F4: 8 | G4: 199 | H4: 0
A5: ORD004 | B5: 45675 | C5: West | D5: Clothing | E5: T-Shirt | F5: 5 | G5: 699 | H5: 0.05
A6: ORD005 | B6: 45680 | C6: North | D6: Electronics | E6: Smart Watch | F6: 2 | G6: 2999 | H6: 0.1
A7: ORD006 | B7: 45686 | C7: South | D7: Clothing | E7: Jeans | F7: 3 | G7: 1299 | H7: 0
A8: ORD007 | B8: 45692 | C8: East | D8: Furniture | E8: Study Table | F8: 2 | G8: 3999 | H8: 0.05
A9: ORD008 | B9: 45697 | C9: West | D9: Electronics | E9: Bluetooth Speaker | F9: 4 | G9: 999 | H9: 0.1
A10: ORD009 | B10: 45702 | C10: North | D10: Office Supplies | E10: Pen Set | F10: 10 | G10: 149 | H10: 0
A11: ORD010 | B11: 45709 | C11: South | D11: Clothing | E11: Jacket | F11: 2 | G11: 2499 | H11: 0.15
A12: ORD011 | B12: 45715 | C12: East | D12: Electronics | E12: Keyboard | F12: 5 | G12: 799 | H12: 0.05
A13: ORD012 | B13: 45719 | C13: West | D13: Furniture | E13: Bookshelf | F13: 3 | G13: 2999 | H13: 0.1
... A61: ORD060 | B61: 46021 | C61: West | D61: Electronics | E61: Wireless Headphones | F61: 6 | G61: 1499 | H61: 0.05

Sheet Pivot_Analysis
A1: Sales by Category | D1: Sales by Region | G1: Monthly Sales | J1: Profit by Category | M1: Quantity by Region
A3: Category | B3: Total Sales | D3: Region | E3: Total Sales | G3: Month | H3: Total Sales | J3: Category | K3: Total Profit | M3: Region | N3: Total Quantity
A4: Clothing | B4: 91388.7 | D4: East | E4: 90894.9 | G4: Jan | H4: 27477.8 | J4: Clothing | K4: 30158.271 | M4: East | N4: 99
A5: Electronics | B5: 120836.05 | D5: North | E5: 79516.8 | G5: Feb | H5: 20728.05 | J5: Electronics | K5: 39875.896 | M5: North | N5: 112
A6: Furniture | B6: 130690.1 | D6: South | E6: 94487.65 | G6: Mar | H6: 33242.9 | J6: Furniture | K6: 43127.733 | M6: South | N6: 111
A7: Office Supplies | B7: 38316 | D7: West | E7: 116331.5 | G7: Apr | H7: 23270.4 | J7: Office Supplies | K7: 12644.28 | M7: West | N7: 82
A8: Grand Total | B8: 381230.85 | D8: Grand Total | E8: 381230.85 | G8: May | H8: 22957.45 | J8: Grand Total | K8: 125806.18 | M8: Grand Total | N8: 404
G9: Jun | H9: 26980.65
G10: Jul | H10: 40561.05
G11: Aug | H11: 26061.4
G12: Sep | H12: 29733.55
G13: Oct | H13: 34725.4
G14: Nov | H14: 33561.55
G15: Dec | H15: 61930.65
G16: Grand Total | H16: 381230.85

Sheet Working_Formula
A1: Order ID | B1: Order Date | C1: Region | D1: Category | E1: Product | F1: Quantity | G1: Unit Price | H1: Discount | I1: Sales | J1: Cost | K1: Profit | L1: Month
A2: ORD001 | B2: 45662 | C2: North | D2: Electronics | E2: Wireless Headphones | F2: 3 | G2: 1499 | H2: 0.05 | I2: =F2*G2*(1-H2) -> 4272.15 | J2: =I2*67% -> 2862.3405 | K2: =I2-J2 -> 1409.8095 | L2: =TEXT(B2,"mmm") -> Jan
A3: ORD002 | B3: 45665 | C3: South | D3: Furniture | E3: Office Chair | F3: 2 | G3: 4999 | H3: 0.1 | I3: =F3*G3*(1-H3) -> 8998.2 | J3: =I3*67% -> 6028.794 | K3: =I3-J3 -> 2969.406 | L3: =TEXT(B3,"mmm") -> Jan
A4: ORD003 | B4: 45669 | C4: East | D4: Office Supplies | E4: Notebook | F4: 8 | G4: 199 | H4: 0 | I4: =F4*G4*(1-H4) -> 1592 | J4: =I4*67% -> 1066.64 | K4: =I4-J4 -> 525.36 | L4: =TEXT(B4,"mmm") -> Jan
A5: ORD004 | B5: 45675 | C5: West | D5: Clothing | E5: T-Shirt | F5: 5 | G5: 699 | H5: 0.05 | I5: =F5*G5*(1-H5) -> 3320.25 | J5: =I5*67% -> 2224.5675 | K5: =I5-J5 -> 1095.6825 | L5: =TEXT(B5,"mmm") -> Jan
A6: ORD005 | B6: 45680 | C6: North | D6: Electronics | E6: Smart Watch | F6: 2 | G6: 2999 | H6: 0.1 | I6: =F6*G6*(1-H6) -> 5398.2 | J6: =I6*67% -> 3616.794 | K6: =I6-J6 -> 1781.406 | L6: =TEXT(B6,"mmm") -> Jan
A7: ORD006 | B7: 45686 | C7: South | D7: Clothing | E7: Jeans | F7: 3 | G7: 1299 | H7: 0 | I7: =F7*G7*(1-H7) -> 3897 | J7: =I7*67% -> 2610.99 | K7: =I7-J7 -> 1286.01 | L7: =TEXT(B7,"mmm") -> Jan
A8: ORD007 | B8: 45692 | C8: East | D8: Furniture | E8: Study Table | F8: 2 | G8: 3999 | H8: 0.05 | I8: =F8*G8*(1-H8) -> 7598.1 | J8: =I8*67% -> 5090.727 | K8: =I8-J8 -> 2507.373 | L8: =TEXT(B8,"mmm") -> Feb
A9: ORD008 | B9: 45697 | C9: West | D9: Electronics | E9: Bluetooth Speaker | F9: 4 | G9: 999 | H9: 0.1 | I9: =F9*G9*(1-H9) -> 3596.4 | J9: =I9*67% -> 2409.588 | K9: =I9-J9 -> 1186.812 | L9: =TEXT(B9,"mmm") -> Feb
A10: ORD009 | B10: 45702 | C10: North | D10: Office Supplies | E10: Pen Set | F10: 10 | G10: 149 | H10: 0 | I10: =F10*G10*(1-H10) -> 1490 | J10: =I10*67% -> 998.3 | K10: =I10-J10 -> 491.7 | L10: =TEXT(B10,"mmm") -> Feb
A11: ORD010 | B11: 45709 | C11: South | D11: Clothing | E11: Jacket | F11: 2 | G11: 2499 | H11: 0.15 | I11: =F11*G11*(1-H11) -> 4248.3 | J11: =I11*67% -> 2846.361 | K11: =I11-J11 -> 1401.939 | L11: =TEXT(B11,"mmm") -> Feb
A12: ORD011 | B12: 45715 | C12: East | D12: Electronics | E12: Keyboard | F12: 5 | G12: 799 | H12: 0.05 | I12: =F12*G12*(1-H12) -> 3795.25 | J12: =I12*67% -> 2542.8175 | K12: =I12-J12 -> 1252.4325 | L12: =TEXT(B12,"mmm") -> Feb
A13: ORD012 | B13: 45719 | C13: West | D13: Furniture | E13: Bookshelf | F13: 3 | G13: 2999 | H13: 0.1 | I13: =F13*G13*(1-H13) -> 8097.3 | J13: =I13*67% -> 5425.191 | K13: =I13-J13 -> 2672.109 | L13: =TEXT(B13,"mmm") -> Mar
... A61: ORD060 | B61: 46021 | C61: West | D61: Electronics | E61: Wireless Headphones | F61: 6 | G61: 1499 | H61: 0.05 | I61: =F61*G61*(1-H61) -> 8544.3 | J61: =I61*67% -> 5724.681 | K61: =I61-J61 -> 2819.619 | L61: =TEXT(B61,"mmm") -> Dec

Sheet Dashboard

Sheet Summary
A1: VEDA Technology – Task 5: Excel Data Analysis
A4: KPI | B4: Value | D4: FormulaAnalysis | E4: Values
A5: Total Sales | B5: =SUM(Working_Formula!I2:I61) -> 381230.85 | D5: Sales in North | E5: =SUMIFS(Working_Formula!I2:I61,Working_Formula!C2:C61,"North") -> 79516.8
A6: Total Cost | B6: =SUM(Working_Formula!J2:J61) -> 255424.67 | D6: Electronics Order Count | E6: =COUNTIFS(Working_Formula!D2:D61,"Electronics") -> 18
A7: Total Profit | B7: =SUM(Working_Formula!K2:K61) -> 125806.18 | D7: Average Electronics Sales | E7: =AVERAGEIFS(Working_Formula!I2:I61,Working_Formula!D2:D61,"Electronics") -> 6713.1139
A8: Total Orders | B8: =COUNTA(Working_Formula!A2:A61) -> 60
A9: Total Quantity | B9: =SUM(Working_Formula!F2:F61) -> 404
A10: Average Order Value | B10: =AVERAGE(Working_Formula!I2:I61) -> 6353.8475
A11: Profit Margin | B11: =B7/B5 -> 0.33
